rdkix/conftest.py
rdkix/license.txt
rdkix/pytest.ini
rdkix/rdBase.pyd
rdkix/RDConfig.py
rdkix/RDLogger.py
rdkix/RDPaths.py
rdkix/RDRandom.py
rdkix/TestRunner.py
rdkix/__init__.py
rdkix/Avalon/pyAvalonTools.pyd
rdkix/Avalon/__init__.py
rdkix/Chem/AllChem.py
rdkix/Chem/BRICS.py
rdkix/Chem/BuildFragmentCatalog.py
rdkix/Chem/ChemicalFeatures.py
rdkix/Chem/ChemicalForceFields.py
rdkix/Chem/Crippen.py
rdkix/Chem/Descriptors.py
rdkix/Chem/Descriptors3D.py
rdkix/Chem/DSViewer.py
rdkix/Chem/EnumerateHeterocycles.py
rdkix/Chem/EnumerateStereoisomers.py
rdkix/Chem/FastSDMolSupplier.py
rdkix/Chem/FeatFinderCLI.py
rdkix/Chem/FilterCatalog.py
rdkix/Chem/FragmentCatalog.py
rdkix/Chem/FragmentMatcher.py
rdkix/Chem/Fragments.py
rdkix/Chem/FunctionalGroups.py
rdkix/Chem/GraphDescriptors.py
rdkix/Chem/Graphs.py
rdkix/Chem/inchi.py
rdkix/Chem/Lipinski.py
rdkix/Chem/MACCSkeys.py
rdkix/Chem/MCS.py
rdkix/Chem/MolCatalog.py
rdkix/Chem/MolSurf.py
rdkix/Chem/PandasPatcher.py
rdkix/Chem/PandasTools.py
rdkix/Chem/PropertyMol.py
rdkix/Chem/PyMol.py
rdkix/Chem/QED.py
rdkix/Chem/Randomize.py
rdkix/Chem/rdAbbreviations.pyd
rdkix/Chem/rdchem.pyd
rdkix/Chem/rdChemicalFeatures.pyd
rdkix/Chem/rdChemReactions.pyd
rdkix/Chem/rdCIPLabeler.pyd
rdkix/Chem/rdCoordGen.pyd
rdkix/Chem/rdDepictor.pyd
rdkix/Chem/rdDeprotect.pyd
rdkix/Chem/rdDetermineBonds.pyd
rdkix/Chem/rdDistGeom.pyd
rdkix/Chem/rdEHTTools.pyd
rdkix/Chem/rdfiltercatalog.pyd
rdkix/Chem/rdFingerprintGenerator.pyd
rdkix/Chem/rdFMCS.pyd
rdkix/Chem/rdForceFieldHelpers.pyd
rdkix/Chem/rdfragcatalog.pyd
rdkix/Chem/rdFreeSASA.pyd
rdkix/Chem/rdGeneralizedSubstruct.pyd
rdkix/Chem/rdinchi.pyd
rdkix/Chem/rdMHFPFingerprint.pyd
rdkix/Chem/rdMMPA.pyd
rdkix/Chem/rdMolAlign.pyd
rdkix/Chem/rdMolCatalog.pyd
rdkix/Chem/rdMolChemicalFeatures.pyd
rdkix/Chem/rdMolDescriptors.pyd
rdkix/Chem/rdMolEnumerator.pyd
rdkix/Chem/rdmolfiles.pyd
rdkix/Chem/rdMolHash.pyd
rdkix/Chem/rdMolInterchange.pyd
rdkix/Chem/rdmolops.pyd
rdkix/Chem/rdMolProcessing.pyd
rdkix-2024.9.2.dist-info/DELVEWHEEL
rdkix-2024.9.2.dist-info/LICENSE.md
rdkix-2024.9.2.dist-info/METADATA
rdkix-2024.9.2.dist-info/RECORD
rdkix-2024.9.2.dist-info/top_level.txt
rdkix-2024.9.2.dist-info/WHEEL
