Metadata-Version: 2.1
Name: rdkix
Version: 2024.9.2
Summary: A collection of chemoinformatics and machine-learning software written in C++ and Python
Home-page: https://github.com/kuelumbus/rdkix
Author: Christopher Kuenneth
Author-email: chris@kuenneth.dev
License: BSD-3-Clause
Project-URL: RDKix, http://rdkit.org/
Project-URL: RDKix on Github, https://github.com/rdkix/rdkix
License-File: LICENSE.md
Requires-Dist: numpy
Requires-Dist: Pillow
